Metadata-Version: 2.1
Name: documentDownloader
Version: 1.1.0
Summary: book118文档下载器
Home-page: https://github.com/OhYee/documentDownloader
Author: OhYee
Author-email: oyohyee@oyohyee.com
License: UNKNOWN
Platform: UNKNOWN
Classifier: Programming Language :: Python :: 3
Classifier: License :: OSI Approved :: MIT License
Classifier: Operating System :: OS Independent
